ngwidgets/__init__.py
ngwidgets/ai_chat.py
ngwidgets/ai_tasks.py
ngwidgets/axes_helper.py
ngwidgets/base_llm.py
ngwidgets/basetest.py
ngwidgets/cmd.py
ngwidgets/color_map.py
ngwidgets/color_schema.py
ngwidgets/combobox.py
ngwidgets/components.py
ngwidgets/components_view.py
ngwidgets/dateparser.py
ngwidgets/debouncer.py
ngwidgets/dict_edit.py
ngwidgets/editor.py
ngwidgets/file_selector.py
ngwidgets/gpxviewer.py
ngwidgets/image_cropper.py
ngwidgets/input_webserver.py
ngwidgets/leaflet_map.py
ngwidgets/llm.py
ngwidgets/local_filepicker.py
ngwidgets/lod_grid.py
ngwidgets/log_view.py
ngwidgets/login.py
ngwidgets/markup_header.py
ngwidgets/ngwidgets_cmd.py
ngwidgets/orjson_response.py
ngwidgets/pdfviewer.js
ngwidgets/pdfviewer.py
ngwidgets/profiler.py
ngwidgets/progress.py
ngwidgets/projects.py
ngwidgets/projects_view.py
ngwidgets/scene_frame.py
ngwidgets/short_url.py
ngwidgets/sso_users_solution.py
ngwidgets/task_runner.py
ngwidgets/test_base_webserver.py
ngwidgets/test_live.py
ngwidgets/tour.py
ngwidgets/tristate.js
ngwidgets/tristate.py
ngwidgets/users.py
ngwidgets/version.py
ngwidgets/webserver.py
ngwidgets/webserver_test.py
ngwidgets/widgets.py
ngwidgets/widgets_demo.py
ngwidgets/wikipedia.py
ngwidgets/yamlable.py
ngwidgets_examples/ai_tasks.yaml
ngwidgets_examples/pdfviewer.html
ngwidgets_examples/show_example
ngwidgets-0.30.4.dist-info/METADATA
ngwidgets-0.30.4.dist-info/WHEEL
ngwidgets-0.30.4.dist-info/entry_points.txt
ngwidgets-0.30.4.dist-info/licenses/LICENSE
ngwidgets-0.30.4.dist-info/RECORD
