Metadata-Version: 2.4
Name: ngwidgets
Version: 0.30.4
Summary: NiceGUI widgets and solution bazaar
Project-URL: Home, https://github.com/WolfgangFahl/nicegui_widgets
Project-URL: Documentation, https://wiki.bitplan.com/index.php/nicegui_widgets
Project-URL: Source, https://github.com/WolfgangFahl/nicegui_widgets
Author-email: Wolfgang Fahl <wf@bitplan.com>
Maintainer-email: Wolfgang Fahl <wf@bitplan.com>
License-Expression: Apache-2.0
License-File: LICENSE
Keywords: components,nicegui,ui
Classifier: Development Status :: 4 - Beta
Classifier: Environment :: Console
Classifier: Intended Audience :: Developers
Classifier: Intended Audience :: Education
Classifier: License :: OSI Approved :: Apache Software License
Classifier: Operating System :: OS Independent
Classifier: Programming Language :: Python :: 3 :: Only
Classifier: Programming Language :: Python :: 3.10
Classifier: Programming Language :: Python :: 3.11
Classifier: Programming Language :: Python :: 3.12
Classifier: Programming Language :: Python :: 3.13
Classifier: Topic :: Software Development :: Libraries :: Python Modules
Requires-Python: >=3.9
Requires-Dist: anthropic>=0.72.0
Requires-Dist: bcrypt>=4.0.1
Requires-Dist: beautifulsoup4
Requires-Dist: colour>=0.1.5
Requires-Dist: dacite>=1.8.1
Requires-Dist: dataclasses-json>=0.6.3
Requires-Dist: gpxpy>=1.6.2
Requires-Dist: nicegui==2.24.2
Requires-Dist: openai>=2.7.1
Requires-Dist: orjson>=3.9.10
Requires-Dist: pybasemkit>=0.1.2
Requires-Dist: pydevd>=2.10.0
Requires-Dist: pygithub>=2.1.1
Requires-Dist: python-dateutil>=2.8.2
Requires-Dist: pytz
Requires-Dist: pyyaml>=6.0.1
Requires-Dist: tdqm
Provides-Extra: mbus
Requires-Dist: pymeterbus>=0.8.4; extra == 'mbus'
Provides-Extra: sso
Requires-Dist: py-3rdparty-mediawiki>=0.17.0; extra == 'sso'
Provides-Extra: test
Requires-Dist: green; extra == 'test'
Requires-Dist: pytest; extra == 'test'
Requires-Dist: pytest-asyncio; extra == 'test'
Requires-Dist: selenium>=4.1.0; extra == 'test'
Requires-Dist: webdriver-manager>=3.8.0; extra == 'test'
